{
	"credit": "Made with Blockbench",
	"textures": {
		"1": "create:block/fan/fan_casing",
		"2": "create:block/fan/fan_side",
		"3": "create:block/gearbox",
		"particle": "create:item/propeller"
	},
	"elements": [
		{
			"from": [0, 0, 0],
			"to": [16, 2, 2],
			"faces": {
				"north": {"uv": [0, 14, 16, 16], "texture": "#2"},
				"east": {"uv": [14, 14, 16, 16], "texture": "#2"},
				"south": {"uv": [0, 14, 16, 16], "texture": "#2"},
				"west": {"uv": [0, 14, 2, 16], "texture": "#2"},
				"down": {"uv": [0, 14, 16, 16], "texture": "#3"}
			}
		},
		{
			"from": [0, 0, 14],
			"to": [16, 2, 16],
			"rotation": {"angle": 0, "axis": "y", "origin": [0, 0, 14]},
			"faces": {
				"north": {"uv": [0, 14, 16, 16], "texture": "#2"},
				"east": {"uv": [0, 14, 2, 16], "texture": "#2"},
				"south": {"uv": [0, 14, 16, 16], "texture": "#2"},
				"west": {"uv": [14, 14, 16, 16], "texture": "#2"},
				"down": {"uv": [0, 0, 16, 2], "texture": "#3"}
			}
		},
		{
			"from": [0, 0, 2],
			"to": [2, 2, 14],
			"rotation": {"angle": 0, "axis": "y", "origin": [0, 0, 2]},
			"faces": {
				"east": {"uv": [2, 14, 14, 16], "texture": "#2"},
				"west": {"uv": [2, 14, 14, 16], "texture": "#2"},
				"down": {"uv": [0, 2, 2, 14], "texture": "#3"}
			}
		},
		{
			"from": [14, 0, 2],
			"to": [16, 2, 14],
			"rotation": {"angle": 0, "axis": "y", "origin": [14, 0, 2]},
			"faces": {
				"east": {"uv": [2, 14, 14, 16], "texture": "#2"},
				"west": {"uv": [2, 14, 14, 16], "texture": "#2"},
				"down": {"uv": [14, 2, 16, 14], "texture": "#3"}
			}
		},
		{
			"name": "hull_outer",
			"from": [0, 2, 0],
			"to": [16, 16, 16],
			"rotation": {"angle": 0, "axis": "y", "origin": [0, 2, 0]},
			"faces": {
				"north": {"uv": [0, 0, 16, 14], "texture": "#2"},
				"east": {"uv": [0, 0, 16, 14], "texture": "#2"},
				"south": {"uv": [0, 0, 16, 14], "texture": "#2"},
				"west": {"uv": [0, 0, 16, 14], "texture": "#2"},
				"up": {"uv": [0, 0, 16, 16], "texture": "#1"},
				"down": {"uv": [0, 0, 16, 16], "texture": "#3"}
			}
		},
		{
			"name": "hull_inner",
			"from": [15, 3, 1],
			"to": [1, 16, 15],
			"rotation": {"angle": 0, "axis": "y", "origin": [15, 3, 17]},
			"faces": {
				"north": {"uv": [1, 1, 15, 14], "texture": "#2"},
				"east": {"uv": [1, 1, 15, 14], "texture": "#2"},
				"south": {"uv": [1, 1, 15, 14], "texture": "#2"},
				"west": {"uv": [1, 1, 15, 14], "texture": "#2"},
				"up": {"uv": [1, 1, 15, 15], "texture": "#1"},
				"down": {"uv": [1, 1, 15, 15], "texture": "#3"}
			}
		}
	],
	"display": {
		"thirdperson_righthand": {
			"rotation": [75, 45, 0],
			"translation": [0, 2.5, 0],
			"scale": [0.375, 0.375, 0.375]
		},
		"thirdperson_lefthand": {
			"rotation": [75, 45, 0],
			"translation": [0, 2.5, 0],
			"scale": [0.375, 0.375, 0.375]
		},
		"firstperson_righthand": {
			"rotation": [0, 45, 0],
			"scale": [0.4, 0.4, 0.4]
		},
		"firstperson_lefthand": {
			"rotation": [0, 225, 0],
			"scale": [0.4, 0.4, 0.4]
		},
		"ground": {
			"translation": [0, 3, 0],
			"scale": [0.25, 0.25, 0.25]
		},
		"gui": {
			"rotation": [30, 225, 0],
			"scale": [0.625, 0.625, 0.625]
		},
		"fixed": {
			"scale": [0.5, 0.5, 0.5]
		}
	}
}